LICENSE
MANIFEST.in
README.md
setup.cfg
setup.py
cdb/__init__.py
cdb/functions.py
cdb/version.py
cdb.egg-info/PKG-INFO
cdb.egg-info/SOURCES.txt
cdb.egg-info/dependency_links.txt
cdb.egg-info/entry_points.txt
cdb.egg-info/not-zip-safe
cdb.egg-info/requires.txt
cdb.egg-info/top_level.txt
cdb/client/__init__.py
cdb/client/generate.py
cdb/logger/__init__.py
cdb/logger/message.py
cdb/main/__init__.py
cdb/templates/__init__.py
cdb/templates/db.go
cdb/utils/__init__.py
cdb/utils/file.py
cdb/utils/module.py
cdb/utils/prompt.py